AudiPy/AudiPy.py
AudiPy/Generator.py
AudiPy/Input.py
AudiPy/Output.py
AudiPy/StandardScalar.py
AudiPy/__init__.py
AudiPy-0.8.dist-info/METADATA
AudiPy-0.8.dist-info/WHEEL
AudiPy-0.8.dist-info/top_level.txt
AudiPy-0.8.dist-info/RECORD
